askharsha/__init__.py
askharsha/core.py
askharsha-0.1.5.dist-info/licenses/LICENSE
askharsha-0.1.5.dist-info/METADATA
askharsha-0.1.5.dist-info/WHEEL
askharsha-0.1.5.dist-info/top_level.txt
askharsha-0.1.5.dist-info/RECORD
