Metadata-Version: 2.4
Name: askharsha
Version: 0.1.5
Summary: A lightweight chatbot module that uses a modern language model API to generate intelligent, clean, and readable responses. Designed for developers who want plain-text replies without markdown clutter.
Author: Alapati Sree Harsha
Author-email: sreeharshaalapati@gmail.com
Requires-Python: >=3.6
License-File: LICENSE
Requires-Dist: requests
Dynamic: author
Dynamic: author-email
Dynamic: description
Dynamic: description-content-type
Dynamic: license-file
Dynamic: requires-dist
Dynamic: requires-python
Dynamic: summary
